{"cord_uid":"q41o6nxs", "sourcedb":"PMC", "sourceid":"PMC4558275", "divid":16, "text":"Consideration should be given to regional One Health approach in the Arctic. Recently developed One Health programme assessment instruments and change models can help the multiple affected stakeholders and communities catalyse transformational changes in behaviours, infrastructure and capacity. Additionally, the tools can be used as metrics to assess progress, and to report success and hurdles to stakeholders, the community and policy makers. A regional One Health approach, with multiple disciplines working together locally, nationally and internationally at the humanÁanimalÁenvironment interface ", "project":"cdlai_CORD-19", "denotations":[]}